tonique/__init__.py
tonique/main.py
tonique-0.2.dist-info/METADATA
tonique-0.2.dist-info/WHEEL
tonique-0.2.dist-info/entry_points.txt
tonique-0.2.dist-info/top_level.txt
tonique-0.2.dist-info/RECORD
