Metadata-Version: 2.2
Name: tonique
Version: 0.2
Requires-Dist: numpy
Dynamic: description
Dynamic: description-content-type
Dynamic: requires-dist
